tabular_theodore/__init__.py
tabular_theodore/src/__init__.py
tabular_theodore/src/combine_styles.py
tabular_theodore/src/get_sections.py
tabular_theodore/src/orchestrator.py
tabular_theodore/src/parse_non_romans_wrapper.py
tabular_theodore/src/parse_pages.py
tabular_theodore/src/parse_romans_wrapper.py
tabular_theodore/src/scrape_ted.py
tabular_theodore/src/simplistic_segmentation.py
tabular_theodore/utils/__init__.py
tabular_theodore/utils/data_quality_checks.py
tabular_theodore/utils/get_blocks.py
tabular_theodore/utils/headers_and_fields.py
tabular_theodore/utils/parse_blocks.py
tabular_theodore-0.7.9.dist-info/METADATA
tabular_theodore-0.7.9.dist-info/WHEEL
tabular_theodore-0.7.9.dist-info/top_level.txt
tabular_theodore-0.7.9.dist-info/RECORD
