Metadata-Version: 2.1
Name: tabular-theodore
Version: 0.7.9
Summary: Download EU Tender data in a convenient format
Home-page: https://github.com/cotopaxih/tabular_theodore
Author: Barnabas Paksi
Author-email: varnavas.shigoto@gmail.com
License: UNKNOWN
Platform: UNKNOWN
Requires-Python: >=3.9
Requires-Dist: pandas >=2.2.2
Requires-Dist: selenium ==4.21.0
Requires-Dist: CurrencyConverter >=0.17.31
Requires-Dist: beautifulsoup4 >4.0.0
